README.md
setup.py
codegenit/__init__.py
codegenit/codegen_package.py
codegenit/codegenit.py
codegenit/dyad.py
codegenit/print_in_color.py
codegenit/project.py
codegenit.egg-info/PKG-INFO
codegenit.egg-info/SOURCES.txt
codegenit.egg-info/dependency_links.txt
codegenit.egg-info/entry_points.txt
codegenit.egg-info/not-zip-safe
codegenit.egg-info/requires.txt
codegenit.egg-info/top_level.txt