Metadata-Version: 1.0
Name: codegenit
Version: 1.2
Summary: Generate a python project from a swagger file.
Home-page: http://github.com/cidrblock/codegenit
Author: Bradley A. Thornton
Author-email: brad@thethorntons.net
License: MIT
Platform: UNKNOWN
